fifo_memory.sv
module fifo_memory #(
    parameter DATA_WIDTH=8,
    parameter ADDR_SIZE=4
) (
    output [DATA_WIDTH-1:0] rdata,
    input [DATA_WIDTH-1:0] wdata,
    input [ADDR_SIZE-1:0] waddr,raddr,
    input wclk_en,wfull,wclk
);
    parameter DEPTH= 1<< ADDR_SIZE;
    reg [DATA_WIDTH-1:0] mem[0:DEPTH-1];
    assign rdata= mem[raddr];
    always@(posedge wclk) begin
        if(wclk_en && !wfull) begin
            mem[waddr]<=wdata;
        end
    end
endmodule

read_pointer_handle.sv
module read_pointer_handle #(
    parameter ADDR_SIZE=4
) (
    output reg rempty,
    output [ADDR_SIZE-1:0] raddr,
    output reg [ADDR_SIZE:0] r_ptr,
    input [ADDR_SIZE:0] r_wptr,// sending it to read clock now
    input rclk,rinc,rrst_n
);  
    reg [ADDR_SIZE:0] curr_rbin;
    wire [ADDR_SIZE:0]rbin_next,rgray_next;
    wire empty;
always @(posedge rclk or negedge rrst_n) begin
    if(!rrst_n) begin
        curr_rbin<=0;
        r_ptr<=0;
        rempty<=1;
    end
    else begin
        curr_rbin<=rbin_next;
        r_ptr<=rgray_next;
        rempty<=empty;
    end
end

    assign rbin_next=curr_rbin+(rinc & ~rempty);
    assign rgray_next=(rbin_next>>1)^rbin_next;
    assign raddr=curr_rbin[ADDR_SIZE-1:0];
    assign empty = (rgray_next==r_wptr);


    
endmodule

write_pointer_handler.sv
module write_pointer_handler#(parameter ADDR_SIZE=4)(
    output  reg wfull, // if the fifo is full or not
    output wire [ADDR_SIZE-1:0] waddr,
    output reg [ADDR_SIZE:0]wptr,//the extra bit is to know if the pointer has wrapped around or not // this is a gray pointer
    input [ADDR_SIZE:0] w_rptr,// readpointer synchronised to write clock its in gray code
    input winc,wclk,wrst_n
);
    reg [ADDR_SIZE:0] wbin;
    wire [ADDR_SIZE:0] wbin_next,wgray_next;
    wire full;
    always @(posedge wclk or negedge wrst_n) begin
        if(!wrst_n) begin
            wbin<=0;
            wptr<=0;
        end
        else begin
            wbin<=wbin_next;
            wptr<=wgray_next;
        end
    end
    assign waddr=wbin[ADDR_SIZE-1:0];
    assign wbin_next=wbin+(winc & ~wfull);
    assign wgray_next=(wbin_next>>1)^wbin_next;
    // the full part
    // gotta compare the gray pointers
    assign full = (wgray_next=={~w_rptr[ADDR_SIZE:ADDR_SIZE-1],w_rptr[ADDR_SIZE-2:0]});

    always@(posedge wclk or negedge wrst_n) begin
        if(!wrst_n) begin
            wfull<=0;
        end
        else begin
            wfull<=full;
        end
    end
endmodule

synchroniser.sv
module synchroniser #(parameter SIZE = 4 )(
    input [SIZE-1:0] din,
    input clk,rst_n,
    output reg [SIZE-1:0] dout
);

    reg [SIZE-1:0] temp;
    always @(posedge clk or negedge rst_n ) begin
        if(!rst_n) begin
            temp<=0;
            dout<=0;
        end
        else begin
            dout<=temp;
            temp<=din;
        end
    end

endmodule

fifo.sv
module fifo #(
    parameter ADDR_SIZE= 4,
    parameter DATA_WIDTH = 8
    ) (
    output [DATA_WIDTH-1:0] rdata,
    output wfull,
    output rempty,
    input [DATA_WIDTH-1:0] wdata,
    input rclk,rinc,rrst_n,
    input wclk,winc,wrst_n
);
//w_r source to destination that is wclk to read clk
    wire [ADDR_SIZE-1:0] waddr, raddr;
    wire [ADDR_SIZE:0] wptr, rptr, w_rptr, r_wptr;
    synchroniser #(ADDR_SIZE+1) wptr_to_rclk(
    .din(wptr),
    .clk(rclk),
    .rst_n(rrst_n),
    .dout(w_rptr)   // write ptr in read domain
);

    
    synchroniser #(ADDR_SIZE+1) rptr_to_wclk(
    .din(rptr),
    .clk(wclk),
    .rst_n(wrst_n),
    .dout(r_wptr)   // read ptr in write domain
);


    write_pointer_handler #(ADDR_SIZE) write_handler(
        .wfull(wfull),
        .waddr(waddr),
        .wptr(wptr),
        .w_rptr(r_wptr),// as this is a write handler signal coming to write from read r_w
        .wclk(wclk),
        .winc(winc),
        .wrst_n(wrst_n)
    );

    read_pointer_handle #(ADDR_SIZE) read_handler(
        .rempty(rempty),
        .raddr(raddr),
        .r_ptr(rptr),
        .r_wptr(w_rptr),
        .rclk(rclk),
        .rinc(rinc),
        .rrst_n(rrst_n)
    );

    fifo_memory #(DATA_WIDTH , ADDR_SIZE) memory(
        .rdata(rdata),
        .wdata(wdata),
        .waddr(waddr),
        .raddr(raddr),
        .wclk_en(winc),
        .wclk(wclk),
        .wfull(wfull)
    );
endmodule

tb.v
`timescale 1ns/1ns

module tb;

    initial begin
        $dumpfile("async_fifo.vcd");
        $dumpvars(0,tb);
        $monitor(" rdata -> %d",rdata);
    end
    localparam DATA_WIDTH = 8,ADDR_SIZE=4;
    wire [DATA_WIDTH-1:0] rdata;
    wire wfull;
    wire rempty;
    reg [DATA_WIDTH-1:0] wdata;
    reg rclk,rinc,rrst_n;
    reg wclk,winc,wrst_n;
    fifo #(ADDR_SIZE,DATA_WIDTH) dut(.*);
    always #5 wclk=~wclk;
    always #10 rclk=~rclk;
    initial begin
        wdata=0;
        rclk=0;
        rinc=0;
        rrst_n=0;
        wclk=0;
        winc=0;
        wrst_n=0;
        @(negedge rclk);
        @(negedge rclk);
        rrst_n=1;
        wrst_n=1;
        @(negedge wclk)
        wdata= 15;
        winc=1;
        @(negedge wclk)
 
        wdata=1;
        @(negedge wclk)
        wdata =3;

        @(negedge rclk)
        winc=0;
        rinc=1;
        wait(rempty == 0); // Wait for data to arrive
        repeat(5) @(posedge rclk);
        $finish;

    end

endmodule

async_fifo.vcd
$date
	Wed Feb 11 19:29:17 2026
$end
$version
	Icarus Verilog
$end
$timescale
	1ns
$end
$scope module tb $end
$var wire 1 ! wfull $end
$var wire 1 " rempty $end
$var wire 8 # rdata [7:0] $end
$var parameter 32 $ ADDR_SIZE $end
$var parameter 32 % DATA_WIDTH $end
$var reg 1 & rclk $end
$var reg 1 ' rinc $end
$var reg 1 ( rrst_n $end
$var reg 1 ) wclk $end
$var reg 8 * wdata [7:0] $end
$var reg 1 + winc $end
$var reg 1 , wrst_n $end
$scope module dut $end
$var wire 1 & rclk $end
$var wire 1 ' rinc $end
$var wire 1 ( rrst_n $end
$var wire 1 ) wclk $end
$var wire 8 - wdata [7:0] $end
$var wire 1 + winc $end
$var wire 1 , wrst_n $end
$var wire 5 . wptr [4:0] $end
$var wire 1 ! wfull $end
$var wire 4 / waddr [3:0] $end
$var wire 5 0 w_rptr [4:0] $end
$var wire 5 1 rptr [4:0] $end
$var wire 1 " rempty $end
$var wire 8 2 rdata [7:0] $end
$var wire 4 3 raddr [3:0] $end
$var wire 5 4 r_wptr [4:0] $end
$var parameter 32 5 ADDR_SIZE $end
$var parameter 32 6 DATA_WIDTH $end
$scope module memory $end
$var wire 8 7 rdata [7:0] $end
$var wire 1 ) wclk $end
$var wire 1 + wclk_en $end
$var wire 8 8 wdata [7:0] $end
$var wire 1 ! wfull $end
$var wire 4 9 waddr [3:0] $end
$var wire 4 : raddr [3:0] $end
$var parameter 32 ; ADDR_SIZE $end
$var parameter 32 < DATA_WIDTH $end
$var parameter 36 = DEPTH $end
$upscope $end
$scope module read_handler $end
$var wire 1 & rclk $end
$var wire 5 > rgray_next [4:0] $end
$var wire 1 ' rinc $end
$var wire 1 ( rrst_n $end
$var wire 5 ? rbin_next [4:0] $end
$var wire 4 @ raddr [3:0] $end
$var wire 5 A r_wptr [4:0] $end
$var wire 1 B empty $end
$var parameter 32 C ADDR_SIZE $end
$var reg 5 D curr_rbin [4:0] $end
$var reg 5 E r_ptr [4:0] $end
$var reg 1 " rempty $end
$upscope $end
$scope module rptr_to_wclk $end
$var wire 1 ) clk $end
$var wire 5 F din [4:0] $end
$var wire 1 , rst_n $end
$var parameter 33 G SIZE $end
$var reg 5 H dout [4:0] $end
$var reg 5 I temp [4:0] $end
$upscope $end
$scope module wptr_to_rclk $end
$var wire 1 & clk $end
$var wire 1 ( rst_n $end
$var wire 5 J din [4:0] $end
$var parameter 33 K SIZE $end
$var reg 5 L dout [4:0] $end
$var reg 5 M temp [4:0] $end
$upscope $end
$scope module write_handler $end
$var wire 5 N w_rptr [4:0] $end
$var wire 1 ) wclk $end
$var wire 5 O wgray_next [4:0] $end
$var wire 1 + winc $end
$var wire 1 , wrst_n $end
$var wire 5 P wbin_next [4:0] $end
$var wire 4 Q waddr [3:0] $end
$var wire 1 R full $end
$var parameter 32 S ADDR_SIZE $end
$var reg 5 T wbin [4:0] $end
$var reg 1 ! wfull $end
$var reg 5 U wptr [4:0] $end
$upscope $end
$upscope $end
$upscope $end
$enddefinitions $end
$comment Show the parameter values. $end
$dumpall
b100 S
b101 K
b101 G
b100 C
b10000 =
b1000 <
b100 ;
b1000 6
b100 5
b1000 %
b100 $
$end
#0
$dumpvars
b0 U
b0 T
0R
b0 Q
b0 P
b0 O
b0 N
b0 M
b0 L
b0 J
b0 I
b0 H
b0 F
b0 E
b0 D
1B
b0 A
b0 @
b0 ?
b0 >
b0 :
b0 9
b0 8
bx 7
b0 4
b0 3
bx 2
b0 1
b0 0
b0 /
b0 .
b0 -
0,
0+
b0 *
0)
0(
0'
0&
bx #
1"
0!
$end
#5
1)
#10
0)
1&
#15
1)
#20
0)
0&
#25
1)
#30
0)
1&
#35
1)
#40
1,
1(
0)
0&
#45
1)
#50
b1 O
b1 P
1+
b1111 *
b1111 -
b1111 8
0)
1&
#55
b1 /
b1 9
b1 Q
b11 O
b1111 #
b1111 2
b1111 7
b1 .
b1 J
b1 U
b10 P
b1 T
1)
#60
b1 *
b1 -
b1 8
0)
0&
#65
b10 /
b10 9
b10 Q
b10 O
b11 .
b11 J
b11 U
b11 P
b10 T
1)
#70
b11 M
b11 *
b11 -
b11 8
0)
1&
#75
b11 /
b11 9
b11 Q
b110 O
b10 .
b10 J
b10 U
b100 P
b11 T
1)
#80
b10 O
b11 P
1'
0+
0)
0&
#85
1)
#90
b10 M
0B
b11 0
b11 A
b11 L
0)
1&
#95
1)
#100
0)
0&
#105
1)
#110
b1 >
b1 ?
b10 0
b10 A
b10 L
0"
0)
1&
#115
1)
#120
0)
0&
#125
1)
#130
0B
b11 >
b1 #
b1 2
b1 7
b1 3
b1 :
b1 @
b1 1
b1 E
b1 F
b10 ?
b1 D
0)
1&
#135
b1 I
1)
#140
0)
0&
#145
b1 4
b1 H
b1 N
1)
#150
1B
b10 >
b11 #
b11 2
b11 7
b10 3
b10 :
b10 @
b11 1
b11 E
b11 F
b11 ?
b10 D
0)
1&
#155
b11 I
1)
#160
0)
0&
#165
b11 4
b11 H
b11 N
1)
#170
1B
b10 >
bx #
bx 2
bx 7
b11 3
b11 :
b11 @
1"
b10 1
b10 E
b10 F
b11 ?
b11 D
0)
1&
#175
b10 I
1)
#180
0)
0&
#185
b10 4
b10 H
b10 N
1)
